{"nombre": "CALZADO OLIMPICA LTDA", "screenshotURL": ".\\results\\screenshots\\calzadoolimpicaltda.png", "ICI": "170013...", "Nit": "8600...", "Razón Social": "CALZADO OLIMPICA LTDA", "Forma Jurídica": "SOCIEDAD LIMITADA", "Departamento": "BOGOTÁ", "Dirección Actual": "CARRERA 71 53...", "Teléfono": "6012...", "Actividad CIIU": "Z9999 - ACTIVIDAD COMERCIAL / INDUSTRIAL AUN NO DEFINIDA POR INFORMA COLOMBIA", "Fecha Constitución": "01/04/1982", "Matrícula Mercantil": "171...", "Fecha Último Dato": "17/06/2020", "Fecha Actualización Cámara Comercio": "28/03/2008"}